amdapi/__init__.py
amdapi/base_classes/__init__.py
amdapi/base_classes/call.py
amdapi/base_classes/client.py
amdapi/base_classes/search_result.py
amdapi/configs/__init__.py
amdapi/configs/default_configs.py
amdapi/exceptions/__init__.py
amdapi/exceptions/api_errors.py
amdapi/exceptions/auth_errors.py
amdapi/exceptions/local_errors.py
amdapi/utils/__init__.py
amdapi/utils/audio.py
amdapi/utils/functions.py
tests/__init__.py
tests/test_gen_b64_key.py
amdapi-0.0.2b9.dist-info/METADATA
amdapi-0.0.2b9.dist-info/WHEEL
amdapi-0.0.2b9.dist-info/top_level.txt
amdapi-0.0.2b9.dist-info/RECORD
