Metadata-Version: 2.1
Name: amdapi
Version: 0.0.2b9
Summary: Python SDK for AMDAPi API
Home-page: https://github.com/AMDA-pi/amda-pi-python-sdk
Download-URL: https://github.com/AMDA-pi/amda-pi-python-sdk
Author: Omer Eltayeb
Author-email: Omer.Eltayeb@amdapi.com
License: UNKNOWN
Project-URL: AMDAPi, https://www.amdapi.com/
Keywords: python,amdapi,AMDA,PI,amdapi-sdk
Platform: UNKNOWN
Classifier: Development Status :: 3 - Alpha
Classifier: Intended Audience :: Customer Service
Classifier: Intended Audience :: System Administrators
Classifier: Intended Audience :: Telecommunications Industry
Classifier: Intended Audience :: Developers
Classifier: Programming Language :: Python :: 3
Classifier: Programming Language :: Python :: 3.7
Classifier: Programming Language :: Python :: 3.8
Classifier: Operating System :: Unix
Classifier: Operating System :: MacOS :: MacOS X
Classifier: Operating System :: Microsoft :: Windows
Requires-Dist: python-dotenv
Requires-Dist: requests
Requires-Dist: pydub
